README.md
setup.py
pyfiles/__init__.py
pyfiles/file.py
pyfiles/mixins.py
pyfiles.egg-info/PKG-INFO
pyfiles.egg-info/SOURCES.txt
pyfiles.egg-info/dependency_links.txt
pyfiles.egg-info/top_level.txt